vxdf/__init__.py
vxdf/__main__.py
vxdf/auth.py
vxdf/cli.py
vxdf/errors.py
vxdf/ingest.py
vxdf/merge_split.py
vxdf/pii.py
vxdf/pq.py
vxdf/py.typed
vxdf/reader.py
vxdf/update.py
vxdf/writer.py
vxdf-0.1.3.dist-info/METADATA
vxdf-0.1.3.dist-info/WHEEL
vxdf-0.1.3.dist-info/entry_points.txt
vxdf-0.1.3.dist-info/top_level.txt
vxdf-0.1.3.dist-info/RECORD
