Metadata-Version: 2.4
Name: vxdf
Version: 0.1.3
Summary: Python implementation of the VXDF (Vector Exchange Data Format) for storing text, metadata and vector embeddings in a single portable file.
Author-email: Kossiso Royce <kossisoroyce@gmail.com>
License: BSD-3-Clause
Project-URL: Homepage, https://github.com/kossisoroyce/vxdf
Project-URL: Documentation, https://kossisoroyce.github.io/vxdf
Keywords: vxdf,vector,embeddings,file-format,rag
Classifier: Programming Language :: Python :: 3
Classifier: License :: OSI Approved :: BSD License
Classifier: Operating System :: OS Independent
Classifier: Intended Audience :: Developers
Classifier: Typing :: Typed
Requires-Python: >=3.8
Requires-Dist: msgpack==1.0.8
Requires-Dist: numpy==1.26.4
Requires-Dist: zstandard<0.24,>=0.22
Requires-Dist: rich>=13
Requires-Dist: argcomplete>=3
Requires-Dist: pdfplumber>=0.10
Requires-Dist: pandas>=2
Requires-Dist: python-docx>=1
Requires-Dist: pyarrow>=15
Requires-Dist: sentence-transformers>=2.7
Requires-Dist: openai>=1
